ubiltools/__init__.py
ubiltools/decorators.py
ubiltools/getkey.py
ubiltools/math.py
ubiltools/sc_support.py
ubiltools/structures.py
ubiltools/term_colors.py
ubiltools-1.0.4.dist-info/LICENSE.txt
ubiltools-1.0.4.dist-info/METADATA
ubiltools-1.0.4.dist-info/WHEEL
ubiltools-1.0.4.dist-info/top_level.txt
ubiltools-1.0.4.dist-info/RECORD
